winrt/_winrt_windows_graphics_printing_workflow.cp314-win_amd64.pyd
winrt/_winrt_windows_graphics_printing_workflow.pyi
winrt/windows/graphics/printing/workflow/__init__.py
winrt/windows/graphics/printing/workflow/py.typed
winrt_windows_graphics_printing_workflow-3.2.1.dist-info/METADATA
winrt_windows_graphics_printing_workflow-3.2.1.dist-info/WHEEL
winrt_windows_graphics_printing_workflow-3.2.1.dist-info/top_level.txt
winrt_windows_graphics_printing_workflow-3.2.1.dist-info/RECORD
